ynab_import/__init__.py
ynab_import/__main__.py
ynab_import/common/__init__.py
ynab_import/common/models.py
ynab_import/common/providers.py
ynab_import/common/settings.py
ynab_import/common/transformers.py
ynab_import/core/__init__.py
ynab_import/core/interactions.py
ynab_import/infra/__init__.py
ynab_import/infra/http.py
ynab_import/infra/ynab.py
ynab_import/revolut/__init__.py
ynab_import/revolut/models.py
ynab_import/revolut/providers.py
ynab_import/revolut/transformers.py
ynab_import/setup.py
ynab_import/swedbank/__init__.py
ynab_import/swedbank/models.py
ynab_import/swedbank/providers.py
ynab_import-0.0.6.dist-info/entry_points.txt
ynab_import-0.0.6.dist-info/LICENSE
ynab_import-0.0.6.dist-info/WHEEL
ynab_import-0.0.6.dist-info/METADATA
ynab_import-0.0.6.dist-info/RECORD
