Metadata-Version: 2.1
Name: ynab-import
Version: 0.0.6
Summary: Automate transaction import troubles to ynab.
Home-page: https://github.com/demonno/ynab-import
License: MIT
Keywords: ynab,api,import,cli
Author: demonno
Author-email: demur.nodia@gmail.com
Requires-Python: >=3.7,<4.0
Classifier: License :: OSI Approved :: MIT License
Classifier: Programming Language :: Python :: 3
Classifier: Programming Language :: Python :: 3.10
Classifier: Programming Language :: Python :: 3.7
Classifier: Programming Language :: Python :: 3.8
Classifier: Programming Language :: Python :: 3.9
Requires-Dist: dataclass-csv (>=1.1,<2.0)
Requires-Dist: pydantic (>=1.8.2,<2.0.0)
Requires-Dist: python-dotenv (>=0.19.2,<0.20.0)
Requires-Dist: typer (>=0.4.0,<0.5.0)
Project-URL: Bug Tracker, https://github.com/demonno/ynab-import/issues
Project-URL: Repository, https://github.com/demonno/ynab-import
